<?xml version="1.0" encoding="UTF-8" standalone="yes"?>
<items>
	<item>
	<title>EPISODIO 1</title>
	<link>https://cdn-s01.mywallpaper-4k-image.net/stream/animes/saint-seiya-omega-dublado/01.mp4/index.m3u8</link>
	</item>
	<item>
	<title>EPISODIO 2</title>
	<link>https://cdn-s01.mywallpaper-4k-image.net/stream/animes/saint-seiya-omega-dublado/02.mp4/index.m3u8</link>
	</item>
	<item>
	<title>EPISODIO 3</title>
	<link>https://cdn-s01.mywallpaper-4k-image.net/stream/animes/saint-seiya-omega-dublado/03.mp4/index.m3u8</link>
	</item>
	<item>
	<title>EPISODIO 4</title>
	<link>https://cdn-s01.mywallpaper-4k-image.net/stream/animes/saint-seiya-omega-dublado/04.mp4/index.m3u8</link>
	</item>
	<item>
	<title>EPISODIO 5</title>
	<link>https://cdn-s01.mywallpaper-4k-image.net/stream/animes/saint-seiya-omega-dublado/05.mp4/index.m3u8</link>
	</item>
	<item>
	<title>EPISODIO 6</title>
	<link>https://cdn-s01.mywallpaper-4k-image.net/stream/animes/saint-seiya-omega-dublado/06.mp4/index.m3u8</link>
	</item>
	<item>
	<title>EPISODIO 7</title>
	<link>https://cdn-s01.mywallpaper-4k-image.net/stream/animes/saint-seiya-omega-dublado/07.mp4/index.m3u8</link>
	</item>
	<item>
	<title>EPISODIO 8</title>
	<link>https://cdn-s01.mywallpaper-4k-image.net/stream/animes/saint-seiya-omega-dublado/08.mp4/index.m3u8</link>
	</item>
	<item>
	<title>EPISODIO 9</title>
	<link>https://cdn-s01.mywallpaper-4k-image.net/stream/animes/saint-seiya-omega-dublado/09.mp4/index.m3u8</link>
	</item>
	<item>
	<title>EPISODIO 10</title>
	<link>https://cdn-s01.mywallpaper-4k-image.net/stream/animes/saint-seiya-omega-dublado/10.mp4/index.m3u8</link>
	</item>
	<item>
	<title>EPISODIO 11</title>
	<link>https://cdn-s01.mywallpaper-4k-image.net/stream/animes/saint-seiya-omega-dublado/11.mp4/index.m3u8</link>
	</item>
	<item>
	<title>EPISODIO 12</title>
	<link>https://cdn-s01.mywallpaper-4k-image.net/stream/animes/saint-seiya-omega-dublado/12.mp4/index.m3u8</link>
	</item>
	<item>
	<title>EPISODIO 13</title>
	<link>https://cdn-s01.mywallpaper-4k-image.net/stream/animes/saint-seiya-omega-dublado/13.mp4/index.m3u8</link>
	</item>
	<item>
	<title>EPISODIO 14</title>
	<link>https://cdn-s01.mywallpaper-4k-image.net/stream/animes/saint-seiya-omega-dublado/14.mp4/index.m3u8</link>
	</item>
	<item>
	<title>EPISODIO 15</title>
	<link>https://cdn-s01.mywallpaper-4k-image.net/stream/animes/saint-seiya-omega-dublado/15.mp4/index.m3u8</link>
	</item>
	<item>
	<title>EPISODIO 16</title>
	<link>https://cdn-s01.mywallpaper-4k-image.net/stream/animes/saint-seiya-omega-dublado/16.mp4/index.m3u8</link>
	</item>
	<item>
	<title>EPISODIO 17</title>
	<link>https://cdn-s01.mywallpaper-4k-image.net/stream/animes/saint-seiya-omega-dublado/17.mp4/index.m3u8</link>
	</item>
	<item>
	<title>EPISODIO 18</title>
	<link>https://cdn-s01.mywallpaper-4k-image.net/stream/animes/saint-seiya-omega-dublado/18.mp4/index.m3u8</link>
	</item>
	<item>
	<title>EPISODIO 19</title>
	<link>https://cdn-s01.mywallpaper-4k-image.net/stream/animes/saint-seiya-omega-dublado/19.mp4/index.m3u8</link>
	</item>
	<item>
	<title>EPISODIO 20</title>
	<link>https://cdn-s01.mywallpaper-4k-image.net/stream/animes/saint-seiya-omega-dublado/20.mp4/index.m3u8</link>
	</item>
	<item>
	<title>EPISODIO 21</title>
	<link>https://cdn-s01.mywallpaper-4k-image.net/stream/animes/saint-seiya-omega-dublado/21.mp4/index.m3u8</link>
	</item>
	<item>
	<title>EPISODIO 22</title>
	<link>https://cdn-s01.mywallpaper-4k-image.net/stream/animes/saint-seiya-omega-dublado/22.mp4/index.m3u8</link>
	</item>
	<item>
	<title>EPISODIO 23</title>
	<link>https://cdn-s01.mywallpaper-4k-image.net/stream/animes/saint-seiya-omega-dublado/23.mp4/index.m3u8</link>
	</item>
	<item>
	<title>EPISODIO 24</title>
	<link>https://cdn-s01.mywallpaper-4k-image.net/stream/animes/saint-seiya-omega-dublado/24.mp4/index.m3u8</link>
	</item>
	<item>
	<title>EPISODIO 25</title>
	<link>https://cdn-s01.mywallpaper-4k-image.net/stream/animes/saint-seiya-omega-dublado/25.mp4/index.m3u8</link>
	</item>
	<item>
	<title>EPISODIO 26</title>
	<link>https://cdn-s01.mywallpaper-4k-image.net/stream/animes/saint-seiya-omega-dublado/26.mp4/index.m3u8</link>
	</item>
	<item>
	<title>EPISODIO 27</title>
	<link>https://cdn-s01.mywallpaper-4k-image.net/stream/animes/saint-seiya-omega-dublado/27.mp4/index.m3u8</link>
	</item>
	<item>
	<title>EPISODIO 28</title>
	<link>https://cdn-s01.mywallpaper-4k-image.net/stream/animes/saint-seiya-omega-dublado/28.mp4/index.m3u8</link>
	</item>
	<item>
	<title>EPISODIO 29</title>
	<link>https://cdn-s01.mywallpaper-4k-image.net/stream/animes/saint-seiya-omega-dublado/29.mp4/index.m3u8</link>
	</item>
	<item>
	<title>EPISODIO 30</title>
	<link>https://cdn-s01.mywallpaper-4k-image.net/stream/animes/saint-seiya-omega-dublado/30.mp4/index.m3u8</link>
	</item>
	<item>
	<title>EPISODIO 31</title>
	<link>https://cdn-s01.mywallpaper-4k-image.net/stream/animes/saint-seiya-omega-dublado/31.mp4/index.m3u8</link>
	</item>
	<item>
	<title>EPISODIO 32</title>
	<link>https://cdn-s01.mywallpaper-4k-image.net/stream/animes/saint-seiya-omega-dublado/32.mp4/index.m3u8</link>
	</item>
	<item>
	<title>EPISODIO 33</title>
	<link>https://cdn-s01.mywallpaper-4k-image.net/stream/animes/saint-seiya-omega-dublado/33.mp4/index.m3u8</link>
	</item>
	<item>
	<title>EPISODIO 34</title>
	<link>https://cdn-s01.mywallpaper-4k-image.net/stream/animes/saint-seiya-omega-dublado/34.mp4/index.m3u8</link>
	</item>
	<item>
	<title>EPISODIO 35</title>
	<link>https://cdn-s01.mywallpaper-4k-image.net/stream/animes/saint-seiya-omega-dublado/35.mp4/index.m3u8</link>
	</item>
	<item>
	<title>EPISODIO 36</title>
	<link>https://cdn-s01.mywallpaper-4k-image.net/stream/animes/saint-seiya-omega-dublado/36.mp4/index.m3u8</link>
	</item>
	<item>
	<title>EPISODIO 37</title>
	<link>https://cdn-s01.mywallpaper-4k-image.net/stream/animes/saint-seiya-omega-dublado/37.mp4/index.m3u8</link>
	</item>
	<item>
	<title>EPISODIO 38</title>
	<link>https://cdn-s01.mywallpaper-4k-image.net/stream/animes/saint-seiya-omega-dublado/38.mp4/index.m3u8</link>
	</item>
	<item>
	<title>EPISODIO 39</title>
	<link>https://cdn-s01.mywallpaper-4k-image.net/stream/animes/saint-seiya-omega-dublado/39.mp4/index.m3u8</link>
	</item>
	<item>
	<title>EPISODIO 40</title>
	<link>https://cdn-s01.mywallpaper-4k-image.net/stream/animes/saint-seiya-omega-dublado/40.mp4/index.m3u8</link>
	</item>
	<item>
	<title>EPISODIO 41</title>
	<link>https://cdn-s01.mywallpaper-4k-image.net/stream/animes/saint-seiya-omega-dublado/41.mp4/index.m3u8</link>
	</item>
	<item>
	<title>EPISODIO 42</title>
	<link>https://cdn-s01.mywallpaper-4k-image.net/stream/animes/saint-seiya-omega-dublado/42.mp4/index.m3u8</link>
	</item>
	<item>
	<title>EPISODIO 43</title>
	<link>https://cdn-s01.mywallpaper-4k-image.net/stream/animes/saint-seiya-omega-dublado/43.mp4/index.m3u8</link>
	</item>
	<item>
	<title>EPISODIO 44</title>
	<link>https://cdn-s01.mywallpaper-4k-image.net/stream/animes/saint-seiya-omega-dublado/44.mp4/index.m3u8</link>
	</item>
	<item>
	<title>EPISODIO 45</title>
	<link>https://cdn-s01.mywallpaper-4k-image.net/stream/animes/saint-seiya-omega-dublado/45.mp4/index.m3u8</link>
	</item>
	<item>
	<title>EPISODIO 46</title>
	<link>https://cdn-s01.mywallpaper-4k-image.net/stream/animes/saint-seiya-omega-dublado/46.mp4/index.m3u8</link>
	</item>
	<item>
	<title>EPISODIO 47</title>
	<link>https://cdn-s01.mywallpaper-4k-image.net/stream/animes/saint-seiya-omega-dublado/47.mp4/index.m3u8</link>
	</item>
	<item>
	<title>EPISODIO 48</title>
	<link>https://cdn-s01.mywallpaper-4k-image.net/stream/animes/saint-seiya-omega-dublado/48.mp4/index.m3u8</link>
	</item>
	<item>
	<title>EPISODIO 49</title>
	<link>https://cdn-s01.mywallpaper-4k-image.net/stream/animes/saint-seiya-omega-dublado/49.mp4/index.m3u8</link>
	</item>
	<item>
	<title>EPISODIO 50</title>
	<link>https://cdn-s01.mywallpaper-4k-image.net/stream/animes/saint-seiya-omega-dublado/50.mp4/index.m3u8</link>
	</item>
	<item>
	<title>EPISODIO 51</title>
	<link>https://cdn-s01.mywallpaper-4k-image.net/stream/animes/saint-seiya-omega-dublado/51.mp4/index.m3u8</link>
	</item>
	<item>
	<title>EPISODIO 52</title>
	<link>https://cdn-s01.mywallpaper-4k-image.net/stream/animes/saint-seiya-omega-dublado/52.mp4/index.m3u8</link>
	</item>
	<item>
	<title>EPISODIO 53</title>
	<link>https://cdn-s01.mywallpaper-4k-image.net/stream/animes/saint-seiya-omega-dublado/53.mp4/index.m3u8</link>
	</item>
	<item>
	<title>EPISODIO 54</title>
	<link>https://cdn-s01.mywallpaper-4k-image.net/stream/animes/saint-seiya-omega-dublado/54.mp4/index.m3u8</link>
	</item>
	<item>
	<title>EPISODIO 55</title>
	<link>https://cdn-s01.mywallpaper-4k-image.net/stream/animes/saint-seiya-omega-dublado/55.mp4/index.m3u8</link>
	</item>
	<item>
	<title>EPISODIO 56</title>
	<link>https://cdn-s01.mywallpaper-4k-image.net/stream/animes/saint-seiya-omega-dublado/56.mp4/index.m3u8</link>
	</item>
	<item>
	<title>EPISODIO 57</title>
	<link>https://cdn-s01.mywallpaper-4k-image.net/stream/animes/saint-seiya-omega-dublado/57.mp4/index.m3u8</link>
	</item>
	<item>
	<title>EPISODIO 58</title>
	<link>https://cdn-s01.mywallpaper-4k-image.net/stream/animes/saint-seiya-omega-dublado/58.mp4/index.m3u8</link>
	</item>
	<item>
	<title>EPISODIO 59</title>
	<link>https://cdn-s01.mywallpaper-4k-image.net/stream/animes/saint-seiya-omega-dublado/59.mp4/index.m3u8</link>
	</item>
	<item>
	<title>EPISODIO 60</title>
	<link>https://cdn-s01.mywallpaper-4k-image.net/stream/animes/saint-seiya-omega-dublado/60.mp4/index.m3u8</link>
	</item>
	<item>
	<title>EPISODIO 61</title>
	<link>https://cdn-s01.mywallpaper-4k-image.net/stream/animes/saint-seiya-omega-dublado/61.mp4/index.m3u8</link>
	</item>
	<item>
	<title>EPISODIO 62</title>
	<link>https://cdn-s01.mywallpaper-4k-image.net/stream/animes/saint-seiya-omega-dublado/62.mp4/index.m3u8</link>
	</item>
	<item>
	<title>EPISODIO 63</title>
	<link>https://cdn-s01.mywallpaper-4k-image.net/stream/animes/saint-seiya-omega-dublado/63.mp4/index.m3u8</link>
	</item>
	<item>
	<title>EPISODIO 64</title>
	<link>https://cdn-s01.mywallpaper-4k-image.net/stream/animes/saint-seiya-omega-dublado/64.mp4/index.m3u8</link>
	</item>
	<item>
	<title>EPISODIO 65</title>
	<link>https://cdn-s01.mywallpaper-4k-image.net/stream/animes/saint-seiya-omega-dublado/65.mp4/index.m3u8</link>
	</item>
	<item>
	<title>EPISODIO 66</title>
	<link>https://cdn-s01.mywallpaper-4k-image.net/stream/animes/saint-seiya-omega-dublado/66.mp4/index.m3u8</link>
	</item>
	<item>
	<title>EPISODIO 67</title>
	<link>https://cdn-s01.mywallpaper-4k-image.net/stream/animes/saint-seiya-omega-dublado/67.mp4/index.m3u8</link>
	</item>
	<item>
	<title>EPISODIO 68</title>
	<link>https://cdn-s01.mywallpaper-4k-image.net/stream/animes/saint-seiya-omega-dublado/68.mp4/index.m3u8</link>
	</item>
	<item>
	<title>EPISODIO 69</title>
	<link>https://cdn-s01.mywallpaper-4k-image.net/stream/animes/saint-seiya-omega-dublado/69.mp4/index.m3u8</link>
	</item>
	<item>
	<title>EPISODIO 70</title>
	<link>https://cdn-s01.mywallpaper-4k-image.net/stream/animes/saint-seiya-omega-dublado/70.mp4/index.m3u8</link>
	</item>
	<item>
	<title>EPISODIO 71</title>
	<link>https://cdn-s01.mywallpaper-4k-image.net/stream/animes/saint-seiya-omega-dublado/71.mp4/index.m3u8</link>
	</item>
	<item>
	<title>EPISODIO 72</title>
	<link>https://cdn-s01.mywallpaper-4k-image.net/stream/animes/saint-seiya-omega-dublado/72.mp4/index.m3u8</link>
	</item>
	<item>
	<title>EPISODIO 73</title>
	<link>https://cdn-s01.mywallpaper-4k-image.net/stream/animes/saint-seiya-omega-dublado/73.mp4/index.m3u8</link>
	</item>
	<item>
	<title>EPISODIO 74</title>
	<link>https://cdn-s01.mywallpaper-4k-image.net/stream/animes/saint-seiya-omega-dublado/74.mp4/index.m3u8</link>
	</item>
	<item>
	<title>EPISODIO 75</title>
	<link>https://cdn-s01.mywallpaper-4k-image.net/stream/animes/saint-seiya-omega-dublado/75.mp4/index.m3u8</link>
	</item>
	<item>
	<title>EPISODIO 76</title>
	<link>https://cdn-s01.mywallpaper-4k-image.net/stream/animes/saint-seiya-omega-dublado/76.mp4/index.m3u8</link>
	</item>
	<item>
	<title>EPISODIO 77</title>
	<link>https://cdn-s01.mywallpaper-4k-image.net/stream/animes/saint-seiya-omega-dublado/77.mp4/index.m3u8</link>
	</item>
	<item>
	<title>EPISODIO 78</title>
	<link>https://cdn-s01.mywallpaper-4k-image.net/stream/animes/saint-seiya-omega-dublado/78.mp4/index.m3u8</link>
	</item>
	<item>
	<title>EPISODIO 79</title>
	<link>https://cdn-s01.mywallpaper-4k-image.net/stream/animes/saint-seiya-omega-dublado/79.mp4/index.m3u8</link>
	</item>
	<item>
	<title>EPISODIO 80</title>
	<link>https://cdn-s01.mywallpaper-4k-image.net/stream/animes/saint-seiya-omega-dublado/80.mp4/index.m3u8</link>
	</item>
	<item>
	<title>EPISODIO 81</title>
	<link>https://cdn-s01.mywallpaper-4k-image.net/stream/animes/saint-seiya-omega-dublado/81.mp4/index.m3u8</link>
	</item>
	<item>
	<title>EPISODIO 82</title>
	<link>https://cdn-s01.mywallpaper-4k-image.net/stream/animes/saint-seiya-omega-dublado/82.mp4/index.m3u8</link>
	</item>
	<item>
	<title>EPISODIO 83</title>
	<link>https://cdn-s01.mywallpaper-4k-image.net/stream/animes/saint-seiya-omega-dublado/83.mp4/index.m3u8</link>
	</item>
	<item>
	<title>EPISODIO 84</title>
	<link>https://cdn-s01.mywallpaper-4k-image.net/stream/animes/saint-seiya-omega-dublado/84.mp4/index.m3u8</link>
	</item>
	<item>
	<title>EPISODIO 85</title>
	<link>https://cdn-s01.mywallpaper-4k-image.net/stream/animes/saint-seiya-omega-dublado/85.mp4/index.m3u8</link>
	</item>
	<item>
	<title>EPISODIO 86</title>
	<link>https://cdn-s01.mywallpaper-4k-image.net/stream/animes/saint-seiya-omega-dublado/86.mp4/index.m3u8</link>
	</item>
	<item>
	<title>EPISODIO 87</title>
	<link>https://cdn-s01.mywallpaper-4k-image.net/stream/animes/saint-seiya-omega-dublado/87.mp4/index.m3u8</link>
	</item>
	<item>
	<title>EPISODIO 88</title>
	<link>https://cdn-s01.mywallpaper-4k-image.net/stream/animes/saint-seiya-omega-dublado/88.mp4/index.m3u8</link>
	</item>
	<item>
	<title>EPISODIO 89</title>
	<link>https://cdn-s01.mywallpaper-4k-image.net/stream/animes/saint-seiya-omega-dublado/89.mp4/index.m3u8</link>
	</item>
	<item>
	<title>EPISODIO 90</title>
	<link>https://cdn-s01.mywallpaper-4k-image.net/stream/animes/saint-seiya-omega-dublado/90.mp4/index.m3u8</link>
	</item>
	<item>
	<title>EPISODIO 91</title>
	<link>https://cdn-s01.mywallpaper-4k-image.net/stream/animes/saint-seiya-omega-dublado/91.mp4/index.m3u8</link>
	</item>
	<item>
	<title>EPISODIO 92</title>
	<link>https://cdn-s01.mywallpaper-4k-image.net/stream/animes/saint-seiya-omega-dublado/92.mp4/index.m3u8</link>
	</item>
	<item>
	<title>EPISODIO 93</title>
	<link>https://cdn-s01.mywallpaper-4k-image.net/stream/animes/saint-seiya-omega-dublado/93.mp4/index.m3u8</link>
	</item>
	<item>
	<title>EPISODIO 94</title>
	<link>https://cdn-s01.mywallpaper-4k-image.net/stream/animes/saint-seiya-omega-dublado/94.mp4/index.m3u8</link>
	</item>
	<item>
	<title>EPISODIO 95</title>
	<link>https://cdn-s01.mywallpaper-4k-image.net/stream/animes/saint-seiya-omega-dublado/95.mp4/index.m3u8</link>
	</item>
	<item>
	<title>EPISODIO 96</title>
	<link>https://cdn-s01.mywallpaper-4k-image.net/stream/animes/saint-seiya-omega-dublado/96.mp4/index.m3u8</link>
	</item>
	<item>
	<title>EPISODIO 97</title>
	<link>https://cdn-s01.mywallpaper-4k-image.net/stream/animes/saint-seiya-omega-dublado/97.mp4/index.m3u8</link>
	</item>
</items>